MANIFEST.in
README.rst
setup.cfg
setup.py
spark_package/__init__.py
spark_package/spark_package.py
spark_package.egg-info/PKG-INFO
spark_package.egg-info/SOURCES.txt
spark_package.egg-info/dependency_links.txt
spark_package.egg-info/entry_points.txt
spark_package.egg-info/top_level.txt
spark_package/resources/
spark_package/resources/.gitignore
spark_package/resources/DESCRIPTION
spark_package/resources/LICENSE
spark_package/resources/MANIFEST.in
spark_package/resources/NAMESPACE
spark_package/resources/README.md
spark_package/resources/Read-and-delete-me
spark_package/resources/__init__.py
spark_package/resources/__init__.pyc
spark_package/resources/build.properties
spark_package/resources/build.sbt
spark_package/resources/documentation.Rd
spark_package/resources/license_temps
spark_package/resources/plugins.sbt
spark_package/resources/requirements.txt
spark_package/resources/sbt
spark_package/resources/sbt-launch-lib.bash
spark_package/resources/setup.cfg
spark_package/resources/setup.py
spark_package/resources/spark-package-deps.txt
spark_package/resources/tests.py
spark_package/resources/license_temps/
spark_package/resources/license_temps/Apache-2.0
spark_package/resources/license_temps/BSD 2-Clause
spark_package/resources/license_temps/BSD 3-Clause
spark_package/resources/license_temps/EPL-1.0
spark_package/resources/license_temps/GPL-2.0
spark_package/resources/license_temps/GPL-3.0
spark_package/resources/license_temps/LGPL-2.1
spark_package/resources/license_temps/LGPL-3.0
spark_package/resources/license_temps/MIT
spark_package/resources/license_temps/MPL-2.0
spark_package/resources/license_temps/__init__.py
spark_package/resources/license_temps/__init__.pyc