Metadata-Version: 1.0
Name: spark-package
Version: 0.4.0
Summary: A command line tool for creating Spark Packages and generating release distributions
Home-page: https://github.com/databricks/spark-package-cmd-tool
Author: Burak Yavuz
Author-email: feedback@spark-packages.org
License: Apache-2.0
Platform: UNKNOWN
